cliptu/__init__.py
cliptu/audio.py
cliptu/channel.py
cliptu/clip.py
cliptu/es.py
cliptu/es_utils.py
cliptu/ffmpeg.py
cliptu/ffprobe.py
cliptu/poetry.lock
cliptu/s3.py
cliptu/s3_es.py
cliptu/s3_utils.py
cliptu/transcribe.py
cliptu/utils.py
cliptu-0.1.3.dist-info/METADATA
cliptu-0.1.3.dist-info/WHEEL
cliptu-0.1.3.dist-info/RECORD
